nova_python-0.1.7.dist-info/METADATA
nova_python-0.1.7.dist-info/WHEEL
nova_python-0.1.7.dist-info/license_files/LICENSE
nova_python.libs/libcrypto-cbcb83f5.so.1.1
nova_python.libs/libssl-32756e7c.so.1.1
nova_python/__init__.py
nova_python/nova_python.cpython-38-aarch64-linux-gnu.so
nova_python-0.1.7.dist-info/RECORD
