Metadata-Version: 2.1
Name: nova-python
Version: 0.1.7
Classifier: Programming Language :: Rust
Classifier: Programming Language :: Python :: Implementation :: CPython
Classifier: Programming Language :: Python :: Implementation :: PyPy
License-File: LICENSE
Summary: 🐍 Python library for accessing the Nova API
Author: Leander <@henceiusegentoo>
Requires-Python: >=3.7
Project-URL: Repo, https://github.com/henceiusegentoo/nova-python
